word_mcp/__init__.py
word_mcp/__main__.py
word_mcp/add_endnote_to_document.py
word_mcp/add_footnote_to_document.py
word_mcp/add_heading.py
word_mcp/add_page_break.py
word_mcp/add_paragraph.py
word_mcp/add_picture.py
word_mcp/add_table.py
word_mcp/create_custom_style.py
word_mcp/create_document.py
word_mcp/customize_footnote_style.py
word_mcp/delete_paragraph.py
word_mcp/exceptions.py
word_mcp/find_text_in_document.py
word_mcp/format_table.py
word_mcp/format_text.py
word_mcp/get_document_info.py
word_mcp/get_document_outline.py
word_mcp/get_document_text.py
word_mcp/get_document_xml.py
word_mcp/get_paragraph_text_from_document.py
word_mcp/insert_header_near_text.py
word_mcp/insert_line_or_paragraph_near_text.py
word_mcp/protect_document.py
word_mcp/search_and_replace_in_document.py
word_mcp/server.py
word_mcp/standalone_server.py
word_mcp/unprotect_document.py
office_word_mcp_uvx_server-0.3.4.dist-info/METADATA
office_word_mcp_uvx_server-0.3.4.dist-info/WHEEL
office_word_mcp_uvx_server-0.3.4.dist-info/entry_points.txt
office_word_mcp_uvx_server-0.3.4.dist-info/top_level.txt
office_word_mcp_uvx_server-0.3.4.dist-info/RECORD
