Metadata-Version: 2.4
Name: office-word-mcp-uvx-server
Version: 0.3.4
Summary: 模型上下文协议（MCP）服务器，允许您在无需安装Microsoft Word 的情况下操作 Word 文件。使用您的AI代理创建、阅读和修改 Word 工作簿。
Home-page: https://git.n.6do.me:8087/mcp/office-word-mcp-uvx-server
Author: fuyingjun
Author-email: fuyingjun <fuyingjun@example.com>
Project-URL: Homepage, https://github.com/your-username/office-word-mcp-uvx-server
Project-URL: Repository, https://github.com/your-username/office-word-mcp-uvx-server
Project-URL: Issues, https://github.com/your-username/office-word-mcp-uvx-server/issues
Requires-Python: >=3.11
Requires-Dist: fastmcp==2.12.4
Requires-Dist: python-docx==1.2.0
Requires-Dist: typer>=0.16.0
